{"0":{"date":1448582400,"AU":398756,"AU2":398756,"N_installs":32062,"DAU":398756,"N_launches":3305728,"Time spent":1345186986.0,"PAU per day":1365,"N_transactions Euros":1962,"Revenue":10939.5257372037,"PAU":1365,"PAU2":1365,"N_users who spent HC per day":194413,"N_transactions HC":794075,"Hard Currency spent":7509992.0,"N_users who spent HC":194413,"N_users who spent HC2":194413},"1":{"date":1448668800,"AU":169242,"AU2":169242,"N_installs":39591,"DAU":422138,"N_launches":3444350,"Time spent":1382512292.0,"PAU per day":1270,"N_transactions Euros":1874,"Revenue":8373.9085258022,"PAU":1062,"PAU2":1062,"N_users who spent HC per day":205746,"N_transactions HC":893270,"Hard Currency spent":8498849.0,"N_users who spent HC":128613,"N_users who spent HC2":128613},"2":{"date":1448755200,"AU":120793,"AU2":120793,"N_installs":41734,"DAU":416521,"N_launches":3437013,"Time spent":1399502793.0,"PAU per day":1209,"N_transactions Euros":1861,"Revenue":7122.3874076381,"PAU":890,"PAU2":890,"N_users who spent HC per day":206851,"N_transactions HC":895197,"Hard Currency spent":7651162.0,"N_users who spent HC":98039,"N_users who spent HC2":98039},"3":{"date":1448841600,"AU":77009,"AU2":77009,"N_installs":30662,"DAU":374658,"N_launches":3009716,"Time spent":975425016.0,"PAU per day":947,"N_transactions Euros":1457,"Revenue":5154.7997484729,"PAU":636,"PAU2":636,"N_users who spent HC per day":159760,"N_transactions HC":646786,"Hard Currency spent":5264495.0,"N_users who spent HC":58835,"N_users who spent HC2":58835},"4":{"date":1448928000,"AU":67248,"AU2":67248,"N_installs":30120,"DAU":368981,"N_launches":2999920,"Time spent":1161090946.0,"PAU per day":937,"N_transactions Euros":1429,"Revenue":5953.8476669863,"PAU":588,"PAU2":588,"N_users who spent HC per day":157176,"N_transactions HC":636208,"Hard Currency spent":4852845.0,"N_users who spent HC":51051,"N_users who spent HC2":51051},"5":{"date":1449014400,"AU":62514,"AU2":62514,"N_installs":30049,"DAU":373155,"N_launches":3076382,"Time spent":1223058212.0,"PAU per day":1005,"N_transactions Euros":1542,"Revenue":6271.8697962984,"PAU":554,"PAU2":554,"N_users who spent HC per day":174883,"N_transactions HC":676260,"Hard Currency spent":5079210.0,"N_users who spent HC":50402,"N_users who spent HC2":50402},"6":{"date":1449100800,"AU":57212,"AU2":57212,"N_installs":28699,"DAU":369791,"N_launches":2994097,"Time spent":1206981353.0,"PAU per day":1275,"N_transactions Euros":1919,"Revenue":7354.4009464905,"PAU":713,"PAU2":713,"N_users who spent HC per day":170361,"N_transactions HC":665927,"Hard Currency spent":5060076.0,"N_users who spent HC":45032,"N_users who spent HC2":45032}}